mpipy/__init__.py
mpipy/bcast_test.py
mpipy/mpi_pyLib.py
mpipy/send_recv.py
mpipy/sr.py
mpipythonpkg-0.1.0.dist-info/METADATA
mpipythonpkg-0.1.0.dist-info/WHEEL
mpipythonpkg-0.1.0.dist-info/top_level.txt
mpipythonpkg-0.1.0.dist-info/RECORD
