Metadata-Version: 2.1
Name: mpipythonpkg
Version: 0.1.0
Summary: MPI_Python library using C-types
Home-page: UNKNOWN
Author: Elkana, Judah, Peter
Author-email: UNKNOWN
License: MIT
Platform: UNKNOWN
